odoo/addons/sales_team_security/README.rst
odoo/addons/sales_team_security/__init__.py
odoo/addons/sales_team_security/__manifest__.py
odoo/addons/sales_team_security/hooks.py
odoo/addons/sales_team_security/i18n/ca.po
odoo/addons/sales_team_security/i18n/de.po
odoo/addons/sales_team_security/i18n/es.po
odoo/addons/sales_team_security/i18n/sales_team_security.pot
odoo/addons/sales_team_security/models/__init__.py
odoo/addons/sales_team_security/models/res_partner.py
odoo/addons/sales_team_security/readme/CONFIGURE.rst
odoo/addons/sales_team_security/readme/CONTRIBUTORS.rst
odoo/addons/sales_team_security/readme/DESCRIPTION.rst
odoo/addons/sales_team_security/readme/INSTALL.rst
odoo/addons/sales_team_security/readme/ROADMAP.rst
odoo/addons/sales_team_security/security/sales_team_security.xml
odoo/addons/sales_team_security/static/description/icon.png
odoo/addons/sales_team_security/static/description/index.html
odoo/addons/sales_team_security/tests/__init__.py
odoo/addons/sales_team_security/tests/test_sales_team_security.py
odoo/addons/sales_team_security/views/res_partner_view.xml
odoo11_addon_sales_team_security-11.0.1.0.0.99.dev11.dist-info/METADATA
odoo11_addon_sales_team_security-11.0.1.0.0.99.dev11.dist-info/WHEEL
odoo11_addon_sales_team_security-11.0.1.0.0.99.dev11.dist-info/top_level.txt
odoo11_addon_sales_team_security-11.0.1.0.0.99.dev11.dist-info/RECORD
